jupyfuncs/__init__.py
jupyfuncs/_version.py
jupyfuncs/chem/__init__.py
jupyfuncs/chem/mol.py
jupyfuncs/chem/norm.py
jupyfuncs/chem/pdb_ext.py
jupyfuncs/chem/scaffold.py
jupyfuncs/chem/shape.py
jupyfuncs/chem/tokenizers.py
jupyfuncs/datasets/city_code.json
jupyfuncs/datasets/defined_BaseFeatures.fdef
jupyfuncs/datasets/las.tsv
jupyfuncs/datasets/route_template.json
jupyfuncs/datasets/vocab.txt
jupyfuncs/dbtools/__init__.py
jupyfuncs/dbtools/pg.py
jupyfuncs/dbtools/query_info.py
jupyfuncs/dl/__init__.py
jupyfuncs/dl/cp.py
jupyfuncs/dl/dataframe.py
jupyfuncs/dl/fp.py
jupyfuncs/dl/list.py
jupyfuncs/dl/model_utils.py
jupyfuncs/dl/tensor.py
jupyfuncs/dl/uncs.py
jupyfuncs/llm/__init__.py
jupyfuncs/llm/extract.py
jupyfuncs/llm/openapi.py
jupyfuncs/network/__init__.py
jupyfuncs/network/proxy.py
jupyfuncs/path/__init__.py
jupyfuncs/path/glob.py
jupyfuncs/path/strings.py
jupyfuncs/show/__init__.py
jupyfuncs/show/pbar.py
jupyfuncs/show/plot.py
jupyfuncs/utils/__init__.py
jupyfuncs/utils/wrappers.py
jupyfuncs-1.1.11.dist-info/METADATA
jupyfuncs-1.1.11.dist-info/WHEEL
jupyfuncs-1.1.11.dist-info/top_level.txt
jupyfuncs-1.1.11.dist-info/RECORD
