Metadata-Version: 2.1
Name: jupyfuncs
Version: 1.1.11
Summary: A collection of functions for Jupyter notebooks
Home-page: https://github.com/huluxiaohuowa/jupyfuncs
Author: Jianxing Hu
Author-email: j.hu@pku.edu.cn
Classifier: Programming Language :: Python :: 3
Classifier: License :: OSI Approved :: MIT License
Classifier: Operating System :: OS Independent
Requires-Python: >=3.6
Requires-Dist: openai
Requires-Dist: tqdm
